detour.py
detour-0.0.1.dist-info/METADATA
detour-0.0.1.dist-info/WHEEL
detour-0.0.1.dist-info/top_level.txt
detour-0.0.1.dist-info/RECORD
